[
    {
        "key": "B002RL8IYK",
        "category": "laptop",
        "name": "RAHUL Chy",
        "seller": "3M",
        "wholePrice": "68",
        "priceFraction": "36",
        "stock": 36,
        "star": 3,
        "starCount": 3245,
        "img": "https://images-na.ssl-images-amazon.com/images/I/415oziPFA0L._AC_US218_.jpg",
        "url": "https://www.amazon.com/gp/slredirect/picassoRedirect.html/ref=pa_sp_atf_electronics_sr_pg1_1?ie=UTF8&adId=A03956601N6RBLKGAP4W1&url=https%3A%2F%2Fwww.amazon.com%2F3M-Privacy-Filter-Widescreen-Laptop%2Fdp%2FB002RL8IYK%2Fref%3Dsr_1_1%3Fs%3Delectronics%26ie%3DUTF8%26qid%3D1499124890%26sr%3D1-1-spons%26keywords%3Dlaptop%26psc%3D1&qualifier=1499124889&id=6267744216991374&widgetName=sp_atf",

        "price": 68.36,
        "shipping": 7.99
    },
    {
        "key": "B01LZ2WZGH",
        "category": "laptop",
        "name": "Manfrotto MB LF-WN-BP camera & laptop backpack for DSLR Lifestyle Windsor, grey",
        "seller": "Manfrotto",
        "wholePrice": "169",
        "priceFraction": "88",
        "stock": 55,
        "star": 2,
        "starCount": 2899,
        "img": "https://i.insider.com/56157fffbd86eff45b8b5079?width=700&format=jpeg&auto=webp",
        "url": "https://www.amazon.com/gp/slredirect/picassoRedirect.html/ref=pa_sp_atf_electronics_sr_pg1_2?ie=UTF8&adId=A04941221ULRUNSJPY1RW&url=https%3A%2F%2Fwww.amazon.com%2FManfrotto-MB-LF-WN-BP-backpack-Lifestyle%2Fdp%2FB01LZ2WZGH%2Fref%3Dsr_1_2%3Fs%3Delectronics%26ie%3DUTF8%26qid%3D1499124890%26sr%3D1-2-spons%26keywords%3Dlaptop%26psc%3D1&qualifier=1499124889&id=6267744216991374&widgetName=sp_atf",
        "features": [],
        "price": 169.88,
        "shipping": 3.99
    },
    {
        "key": "B01LZ2WZGH",
        "category": "laptop",
        "name": "Manfrotto MB LF-WN-BP camera & laptop backpack for DSLR Lifestyle Windsor, grey",
        "seller": "Manfrotto",
        "wholePrice": "169",
        "priceFraction": "88",
        "stock": 55,
        "star": 2,
        "starCount": 2899,
        "img": "https://img-cdn.inc.com/image/upload/w_1920,h_1080,c_fill/images/panoramic/GettyImages-187969754_441409_w6ga1c.jpg",
        "url": "https://www.amazon.com/gp/slredirect/picassoRedirect.html/ref=pa_sp_atf_electronics_sr_pg1_2?ie=UTF8&adId=A04941221ULRUNSJPY1RW&url=https%3A%2F%2Fwww.amazon.com%2FManfrotto-MB-LF-WN-BP-backpack-Lifestyle%2Fdp%2FB01LZ2WZGH%2Fref%3Dsr_1_2%3Fs%3Delectronics%26ie%3DUTF8%26qid%3D1499124890%26sr%3D1-2-spons%26keywords%3Dlaptop%26psc%3D1&qualifier=1499124889&id=6267744216991374&widgetName=sp_atf",
        "features": [],
        "price": 169.88,
        "shipping": 3.99
    }

]